pweb/__init__.py
pweb/conf/__init__.py
pweb/conf/global_settings.py
pweb/db/__init__.py
pweb/db/client.py
pweb/examples/__init__.py
pweb/examples/settings.py
pweb/examples/urls.py
pweb/examples/wsgi.py
pweb/examples/index/__init__.py
pweb/examples/index/actions.py
pweb/examples/index/rndcode.py
pweb/examples/media/__init__.py
pweb/examples/templates/__init__.py
pweb/handlers/__init__.py
pweb/handlers/application.py
pweb/handlers/wsgi.py
pweb/handlers/wsgiserver.py
pweb/http/__init__.py
pweb/http/debugerror.py
pweb/http/resultstruct.py
pweb/middleware/__init__.py
pweb/middleware/session.py
pweb/template/__init__.py
pweb/template/_compiler.py
pweb/template/_render.py
pweb/template/_template.py
pweb/utils/__init__.py
pweb/utils/browser.py
pweb/utils/datastructs.py
pweb/utils/encoding.py
pweb/utils/imgcode.py
pweb/utils/importlib.py
pweb/utils/log.py
pweb/utils/net.py
pweb/utils/py3helpers.py
pweb/utils/python23.py
pweb-1.5.1.data/scripts/pweb-admin.py
pweb-1.5.1.dist-info/METADATA
pweb-1.5.1.dist-info/WHEEL
pweb-1.5.1.dist-info/top_level.txt
pweb-1.5.1.dist-info/RECORD
